Metadata-Version: 2.1
Name: a-pandas-ex-dumpsys-to-df
Version: 0.10
Summary: ADB 'dumpsys package' to Pandas DataFrame
Home-page: https://github.com/hansalemaos/a_pandas_ex_dumpsys_to_df
Author: Johannes Fischer
Author-email: <aulasparticularesdealemaosp@gmail.com>
License: MIT
Keywords: pandas,df,DataFrame,ADB,Android,dumpsys
Classifier: Development Status :: 4 - Beta
Classifier: Programming Language :: Python :: 3 :: Only
Classifier: Programming Language :: Python :: 3.9
Classifier: Topic :: Scientific/Engineering :: Visualization
Classifier: Topic :: Software Development :: Libraries :: Python Modules
Classifier: Topic :: Text Editors :: Text Processing
Classifier: Topic :: Text Processing :: General
Classifier: Topic :: Text Processing :: Indexing
Classifier: Topic :: Text Processing :: Filters
Classifier: Topic :: Utilities
License-File: LICENSE.rst
Requires-Dist: a-pandas-ex-plode-tool
Requires-Dist: a-pandas-ex-split-on-common-string
Requires-Dist: pandas
Requires-Dist: regex
